nonebot_plugin_dcqg_relay/__init__.py
nonebot_plugin_dcqg_relay/config.py
nonebot_plugin_dcqg_relay/dc_to_qq.py
nonebot_plugin_dcqg_relay/migrations/0105684994ff_move_from_sqlite.py
nonebot_plugin_dcqg_relay/migrations/a9b783356705_init_db.py
nonebot_plugin_dcqg_relay/model.py
nonebot_plugin_dcqg_relay/qq_emoji_dict.py
nonebot_plugin_dcqg_relay/qq_to_dc.py
nonebot_plugin_dcqg_relay/utils.py
nonebot_plugin_dcqg_relay-1.1.4.dist-info/METADATA
nonebot_plugin_dcqg_relay-1.1.4.dist-info/WHEEL
nonebot_plugin_dcqg_relay-1.1.4.dist-info/licenses/LICENSE
nonebot_plugin_dcqg_relay-1.1.4.dist-info/RECORD
