Metadata-Version: 2.4
Name: nonebot-plugin-dcqg-relay
Version: 1.1.4
Summary: 在QQ频道与 Discord 之间同步消息的 nonebot2 插件
License: MIT
License-File: LICENSE
Author: Autuamn_End
Author-email: autuamn@qq.com
Requires-Python: >=3.9,<4.0
Classifier: License :: OSI Approved :: MIT License
Classifier: Programming Language :: Python :: 3
Classifier: Programming Language :: Python :: 3.9
Classifier: Programming Language :: Python :: 3.10
Classifier: Programming Language :: Python :: 3.11
Classifier: Programming Language :: Python :: 3.12
Classifier: Programming Language :: Python :: 3.13
Classifier: Programming Language :: Python :: 3.14
Requires-Dist: cryptography (<44.0.0) ; python_full_version == "3.9.0" or python_full_version == "3.9.1"
Requires-Dist: cryptography (>=44.0.1,<45.0.0) ; python_full_version != "3.9.0" and python_full_version != "3.9.1"
Requires-Dist: filetype (>=1.2.0,<2.0.0)
Requires-Dist: nonebot-adapter-discord (>=0.1.8,<0.2.0)
Requires-Dist: nonebot-adapter-qq (>=1.4.3,<2.0.0)
Requires-Dist: nonebot-plugin-localstore (>=0.6.0,<0.7.0)
Requires-Dist: nonebot-plugin-orm[default] (>=0.7.3,<0.8.0)
Requires-Dist: nonebot2[aiohttp] (>=2.2.1,<3.0.0)
Requires-Dist: pillow (>=10.3.0,<11.0.0)
